{"P34": {"supervisions": null, "lectures": 8, "prerequisite_for": [], "past_exam_questions": null, "description": "\n\n\n", "course_name": "Advanced Computer Design", "course_code": "P34", "course_url": "https://www.cl.cam.ac.uk/teaching/1213/P34", "lecturers": ["swm11"], "year": "1213", "tripos_part": "3", "michaelmas": true, "lent": false, "easter": false}, "L11": {"supervisions": null, "lectures": 16, "prerequisite_for": [], "past_exam_questions": null, "description": "\n\n\n", "course_name": "Algebraic Path Problems, with applications to Internet Routing", "course_code": "L11", "course_url": "https://www.cl.cam.ac.uk/teaching/1213/L11", "lecturers": ["tgg22"], "year": "1213", "tripos_part": "3", "michaelmas": true, "lent": false, "easter": false}, "L18": {"supervisions": null, "lectures": null, "prerequisite_for": [], "past_exam_questions": null, "description": "\n\n\n", "course_name": "Automated Reasoning", "course_code": "L18", "course_url": "https://www.cl.cam.ac.uk/teaching/1213/L18", "lecturers": ["mj201"], "year": "1213", "tripos_part": "3", "michaelmas": true, "lent": false, "easter": false}, "L108": {"supervisions": null, "lectures": null, "prerequisite_for": [], "past_exam_questions": null, "description": "\n\n\n", "course_name": "Category Theory and Logic", "course_code": "L108", "course_url": "https://www.cl.cam.ac.uk/teaching/1213/L108", "lecturers": ["ss368"], "year": "1213", "tripos_part": "3", "michaelmas": true, "lent": false, "easter": false}, "R05": {"supervisions": null, "lectures": 8, "prerequisite_for": [], "past_exam_questions": null, "description": "\n\n\n", "course_name": "Chip Multiprocessors", "course_code": "R05", "course_url": "https://www.cl.cam.ac.uk/teaching/1213/R05", "lecturers": ["rdm34"], "year": "1213", "tripos_part": "3", "michaelmas": true, "lent": false, "easter": false}, "R209": {"supervisions": null, "lectures": 8, "prerequisite_for": [], "past_exam_questions": null, "description": "\n\n\n", "course_name": "Computer Security: Principles and Foundations", "course_code": "R209", "course_url": "https://www.cl.cam.ac.uk/teaching/1213/R209", "lecturers": ["rja14", "fms27", "sjm217", "rnw24"], "year": "1213", "tripos_part": "3", "michaelmas": true, "lent": false, "easter": false}, "E4F8": {"supervisions": null, "lectures": 16, "prerequisite_for": [], "past_exam_questions": null, "description": "\n\n\n", "course_name": "Image Processing and Image Coding", "course_code": "E4F8", "course_url": "https://www.cl.cam.ac.uk/teaching/1213/E4F8", "lecturers": [], "year": "1213", "tripos_part": "3", "michaelmas": true, "lent": false, "easter": false}, "R03": {"supervisions": null, "lectures": 8, "prerequisite_for": [], "past_exam_questions": null, "description": "\n\n\n", "course_name": "Innovative User Interfaces", "course_code": "R03", "course_url": "https://www.cl.cam.ac.uk/teaching/1213/R03", "lecturers": ["pr10"], "year": "1213", "tripos_part": "3", "michaelmas": true, "lent": false, "easter": false}, "L100": {"supervisions": null, "lectures": 16, "prerequisite_for": [], "past_exam_questions": null, "description": "\n\n\n", "course_name": "Introduction to Natural Language Processing", "course_code": "L100", "course_url": "https://www.cl.cam.ac.uk/teaching/1213/L100", "lecturers": ["aac10", "sc609"], "year": "1213", "tripos_part": "3", "michaelmas": true, "lent": false, "easter": false}, "R07": {"supervisions": null, "lectures": null, "prerequisite_for": [], "past_exam_questions": null, "description": "\n\n\n", "course_name": "Introductory Logic", "course_code": "R07", "course_url": "https://www.cl.cam.ac.uk/teaching/1213/R07", "lecturers": ["bh288"], "year": "1213", "tripos_part": "3", "michaelmas": true, "lent": false, "easter": false}, "P31": {"supervisions": null, "lectures": 8, "prerequisite_for": [], "past_exam_questions": null, "description": "\n\n\n", "course_name": "Low Power Embedded Systems Programming", "course_code": "P31", "course_url": "https://www.cl.cam.ac.uk/teaching/1213/P31", "lecturers": ["ijw24", "bdj23"], "year": "1213", "tripos_part": "3", "michaelmas": true, "lent": false, "easter": false}, "R204": {"supervisions": null, "lectures": 8, "prerequisite_for": [], "past_exam_questions": null, "description": "\n\n\n", "course_name": "Multicore Semantics and Programming", "course_code": "R204", "course_url": "https://www.cl.cam.ac.uk/teaching/1213/R204", "lecturers": ["pes20", "tlh20"], "year": "1213", "tripos_part": "3", "michaelmas": true, "lent": false, "easter": false}, "R02": {"supervisions": null, "lectures": 16, "prerequisite_for": [], "past_exam_questions": null, "description": "\n\n\n", "course_name": "Network Architectures", "course_code": "R02", "course_url": "https://www.cl.cam.ac.uk/teaching/1213/R02", "lecturers": ["jac22"], "year": "1213", "tripos_part": "3", "michaelmas": true, "lent": false, "easter": false}, "P36": {"supervisions": 6, "lectures": 8, "prerequisite_for": [], "past_exam_questions": null, "description": "\n\n\n", "course_name": "Programming for Mobiles", "course_code": "P36", "course_url": "https://www.cl.cam.ac.uk/teaching/1213/P36", "lecturers": ["acr31"], "year": "1213", "tripos_part": "3", "michaelmas": true, "lent": false, "easter": false}, "C00": {"supervisions": null, "lectures": 16, "prerequisite_for": [], "past_exam_questions": null, "description": "\n\n\n", "course_name": "Research Skills", "course_code": "C00", "course_url": "https://www.cl.cam.ac.uk/teaching/1213/C00", "lecturers": ["nad10"], "year": "1213", "tripos_part": "3", "michaelmas": true, "lent": false, "easter": false}, "L106": {"supervisions": null, "lectures": 14, "prerequisite_for": [], "past_exam_questions": null, "description": "\n\n\n", "course_name": "Spoken Language Processing", "course_code": "L106", "course_url": "https://www.cl.cam.ac.uk/teaching/1213/L106", "lecturers": [], "year": "1213", "tripos_part": "3", "michaelmas": true, "lent": false, "easter": false}, "L113": {"supervisions": null, "lectures": 8, "prerequisite_for": [], "past_exam_questions": null, "description": "\n\n\n", "course_name": "Word Meaning and Discourse Understanding", "course_code": "L113", "course_url": "https://www.cl.cam.ac.uk/teaching/1213/L113", "lecturers": ["sht25"], "year": "1213", "tripos_part": "3", "michaelmas": true, "lent": false, "easter": false}, "L22": {"supervisions": null, "lectures": 8, "prerequisite_for": [], "past_exam_questions": null, "description": "\n\n\n", "course_name": "Advanced Topics in Concurrency", "course_code": "L22", "course_url": "https://www.cl.cam.ac.uk/teaching/1213/L22", "lecturers": ["gw104"], "year": "1213", "tripos_part": "3", "michaelmas": false, "lent": true, "easter": false}, "R211": {"supervisions": null, "lectures": null, "prerequisite_for": [], "past_exam_questions": null, "description": "\n\n\n", "course_name": "Biomedical Informatics", "course_code": "R211", "course_url": "https://www.cl.cam.ac.uk/teaching/1213/R211", "lecturers": ["alk23", "pl219"], "year": "1213", "tripos_part": "3", "michaelmas": false, "lent": true, "easter": false}, "P33": {"supervisions": 2, "lectures": 1, "prerequisite_for": [], "past_exam_questions": null, "description": "\n\n\n", "course_name": "Building an Internet Router", "course_code": "P33", "course_url": "https://www.cl.cam.ac.uk/teaching/1213/P33", "lecturers": ["awm22"], "year": "1213", "tripos_part": "3", "michaelmas": false, "lent": true, "easter": false}, "L24": {"supervisions": null, "lectures": 8, "prerequisite_for": [], "past_exam_questions": null, "description": "\n\n\n", "course_name": "Categorical Models of Computational Languages", "course_code": "L24", "course_url": "https://www.cl.cam.ac.uk/teaching/1213/L24", "lecturers": ["mpf23"], "year": "1213", "tripos_part": "3", "michaelmas": false, "lent": true, "easter": false}, "R210": {"supervisions": null, "lectures": 8, "prerequisite_for": [], "past_exam_questions": null, "description": "\n\n\n", "course_name": "Computer Security: Current Applications and Research", "course_code": "R210", "course_url": "https://www.cl.cam.ac.uk/teaching/1213/R210", "lecturers": ["rja14", "sjm217", "rnw24"], "year": "1213", "tripos_part": "3", "michaelmas": false, "lent": true, "easter": false}, "R202": {"supervisions": null, "lectures": 8, "prerequisite_for": [], "past_exam_questions": null, "description": "\n\n\n", "course_name": "Data Centric Networking", "course_code": "R202", "course_url": "https://www.cl.cam.ac.uk/teaching/1213/R202", "lecturers": ["ey204"], "year": "1213", "tripos_part": "3", "michaelmas": false, "lent": true, "easter": false}, "L110": {"supervisions": 2, "lectures": 14, "prerequisite_for": [], "past_exam_questions": null, "description": "\n\n\n", "course_name": "Flows in Networks", "course_code": "L110", "course_url": "https://www.cl.cam.ac.uk/teaching/1213/L110", "lecturers": ["rg31"], "year": "1213", "tripos_part": "3", "michaelmas": false, "lent": true, "easter": false}, "L21": {"supervisions": 4, "lectures": 12, "prerequisite_for": [], "past_exam_questions": null, "description": "\n\n\n", "course_name": "Interactive Formal Verification", "course_code": "L21", "course_url": "https://www.cl.cam.ac.uk/teaching/1213/L21", "lecturers": ["lp15"], "year": "1213", "tripos_part": "3", "michaelmas": false, "lent": true, "easter": false}, "R207": {"supervisions": null, "lectures": 8, "prerequisite_for": [], "past_exam_questions": null, "description": "\n\n\n", "course_name": "Language and Concepts", "course_code": "R207", "course_url": "https://www.cl.cam.ac.uk/teaching/1213/R207", "lecturers": ["aac10"], "year": "1213", "tripos_part": "3", "michaelmas": false, "lent": true, "easter": false}, "L101": {"supervisions": 8, "lectures": 8, "prerequisite_for": [], "past_exam_questions": null, "description": "\n\n\n", "course_name": "Machine Learning for Language Processing", "course_code": "L101", "course_url": "https://www.cl.cam.ac.uk/teaching/1213/L101", "lecturers": ["ejb1", "sc609"], "year": "1213", "tripos_part": "3", "michaelmas": false, "lent": true, "easter": false}, "L23": {"supervisions": null, "lectures": null, "prerequisite_for": [], "past_exam_questions": null, "description": "\n\n\n", "course_name": "Nominal Sets and Their Applications", "course_code": "L23", "course_url": "https://www.cl.cam.ac.uk/teaching/1213/L23", "lecturers": ["amp12"], "year": "1213", "tripos_part": "3", "michaelmas": false, "lent": true, "easter": false}, "L109": {"supervisions": null, "lectures": 16, "prerequisite_for": [], "past_exam_questions": null, "description": "\n\n\n", "course_name": "Social and Technological Network Analysis", "course_code": "L109", "course_url": "https://www.cl.cam.ac.uk/teaching/1213/L109", "lecturers": ["cm542"], "year": "1213", "tripos_part": "3", "michaelmas": false, "lent": true, "easter": false}, "L102": {"supervisions": null, "lectures": 10, "prerequisite_for": [], "past_exam_questions": null, "description": "\n\n\n", "course_name": "Statistical Machine Translation", "course_code": "L102", "course_url": "https://www.cl.cam.ac.uk/teaching/1213/L102", "lecturers": ["sc609"], "year": "1213", "tripos_part": "3", "michaelmas": false, "lent": true, "easter": false}, "L107": {"supervisions": null, "lectures": 16, "prerequisite_for": [], "past_exam_questions": null, "description": "\n\n\n", "course_name": "Syntax and Semantics of Natural Language", "course_code": "L107", "course_url": "https://www.cl.cam.ac.uk/teaching/1213/L107", "lecturers": ["ejb1", "sc609"], "year": "1213", "tripos_part": "3", "michaelmas": false, "lent": true, "easter": false}, "P35": {"supervisions": 8, "lectures": 8, "prerequisite_for": [], "past_exam_questions": null, "description": "\n\n\n", "course_name": "System on Chip Design and Modelling", "course_code": "P35", "course_url": "https://www.cl.cam.ac.uk/teaching/1213/P35", "lecturers": ["djg11"], "year": "1213", "tripos_part": "3", "michaelmas": false, "lent": true, "easter": false}, "L15": {"supervisions": null, "lectures": 4, "prerequisite_for": [], "past_exam_questions": null, "description": "\n\n\n", "course_name": "Topics in Logic and Complexity", "course_code": "L15", "course_url": "https://www.cl.cam.ac.uk/teaching/1213/L15", "lecturers": ["ad260"], "year": "1213", "tripos_part": "3", "michaelmas": false, "lent": true, "easter": false}, "R201": {"supervisions": 4, "lectures": 4, "prerequisite_for": [], "past_exam_questions": null, "description": "\n\n\n", "course_name": "Usability of Programming Languages", "course_code": "R201", "course_url": "https://www.cl.cam.ac.uk/teaching/1213/R201", "lecturers": ["afb21"], "year": "1213", "tripos_part": "3", "michaelmas": false, "lent": true, "easter": false}}